llms.txt
docs/md/llms.md
docs/md/_configuration_table/core-settings.md
docs/md/_configuration_table/index.md
docs/md/_configuration_table/optional-settings.md
docs/md/advanced_configuration/caching-backends.md
docs/md/advanced_configuration/cascade-deletes.md
docs/md/advanced_configuration/case-conventions.md
docs/md/advanced_configuration/cors.md
docs/md/advanced_configuration/extensions-validators-and-hooks.md
docs/md/advanced_configuration/full-auto-mode.md
docs/md/advanced_configuration/index.md
docs/md/advanced_configuration/initialising-with-optional-features.md
docs/md/advanced_configuration/nested-model-creation.md
docs/md/advanced_configuration/query-parameter-controls.md
docs/md/advanced_configuration/rate-limiting.md
docs/md/advanced_configuration/response-metadata.md
docs/md/advanced_configuration/soft-delete.md
docs/md/advanced_demo/index.md
docs/md/advanced_demo/key-points.md
docs/md/advanced_demo/run-the-demo.md
docs/md/auth_cookbook/api-key-strategies.md
docs/md/auth_cookbook/basic-authentication.md
docs/md/auth_cookbook/contents.md
docs/md/auth_cookbook/further-reading.md
docs/md/auth_cookbook/index.md
docs/md/auth_cookbook/jwt-patterns.md
docs/md/auth_cookbook/multi-tenant-considerations.md
docs/md/auth_cookbook/role-mapping-examples.md
docs/md/authentication/access-policies.md
docs/md/authentication/api-key-authentication.md
docs/md/authentication/auth-requirements.md
docs/md/authentication/basic-authentication.md
docs/md/authentication/config-driven-roles.md
docs/md/authentication/cookie-helpers.md
docs/md/authentication/custom-authentication.md
docs/md/authentication/error-responses.md
docs/md/authentication/index.md
docs/md/authentication/jwt-authentication.md
docs/md/authentication/role-based-access.md
docs/md/authentication/token-providers.md
docs/md/authentication/troubleshooting.md
docs/md/caching/backends.md
docs/md/caching/example.md
docs/md/caching/index.md
docs/md/configuration/cascade-delete-settings.md
flarchitect-1.5.6.dist-info/METADATA
flarchitect-1.5.6.dist-info/WHEEL
flarchitect-1.5.6.dist-info/entry_points.txt
flarchitect-1.5.6.dist-info/licenses/LICENSE
flarchitect-1.5.6.dist-info/RECORD
