Metadata-Version: 2.4
Name: flarchitect
Version: 1.5.6
Summary: Automatic RESTful API generator with redoc
Author-email: "arched.dev (Lewis Morris)" <hello@arched.dev>
License-File: LICENSE
Classifier: Development Status :: 4 - Beta
Classifier: Intended Audience :: Developers
Classifier: Programming Language :: Python
Requires-Python: >=3.10
Requires-Dist: apispec>=6.3.1
Requires-Dist: beautifulsoup4>=4.13.4
Requires-Dist: colorama>=0.4.6
Requires-Dist: dicttoxml>=1.7.16
Requires-Dist: docutils
Requires-Dist: flask-jwt-extended>=4.6.0
Requires-Dist: flask-limiter>=3.5.0
Requires-Dist: flask-login>=0.6.3
Requires-Dist: flask-sqlalchemy>=3.0.5
Requires-Dist: flask>=2.2.5
Requires-Dist: graphene>=3.3.0
Requires-Dist: inflect>=7.5.0
Requires-Dist: marshmallow-sqlalchemy>=0.29.0
Requires-Dist: numpy>=1.21.6
Requires-Dist: pymongo>=4.7.3
Requires-Dist: redis>=5.0.8
Requires-Dist: requests>=2.31.0
Requires-Dist: sqlalchemy-utils>=0.41.2
Requires-Dist: validators>=0.20.0
Provides-Extra: cache
Requires-Dist: flask-caching>=2.1.0; extra == 'cache'
Provides-Extra: dev
Requires-Dist: isort; extra == 'dev'
Requires-Dist: pytest-cov>=4.1.0; extra == 'dev'
Requires-Dist: pytest>=7.4.4; extra == 'dev'
Requires-Dist: ruff; extra == 'dev'
Provides-Extra: docs
Requires-Dist: coverage-badge>=1.1.0; extra == 'docs'
Requires-Dist: furo>=2024.1.29; extra == 'docs'
Requires-Dist: myst-parser>=3.0.0; extra == 'docs'
Requires-Dist: sphinx-copybutton>=0.5.2; extra == 'docs'
Requires-Dist: sphinx-design>=0.6.1; extra == 'docs'
Requires-Dist: sphinx>=8; extra == 'docs'
Requires-Dist: sphinxext-opengraph>=0.9.1; extra == 'docs'
Provides-Extra: graphql
Requires-Dist: graphene>=3.3; extra == 'graphql'
Provides-Extra: mcp
Requires-Dist: docutils>=0.21; extra == 'mcp'
Requires-Dist: fastmcp>=2.12.3; extra == 'mcp'
Requires-Dist: mcp[cli]>=1.14.0; extra == 'mcp'
Provides-Extra: release
Requires-Dist: python-semantic-release>=10.3.1; extra == 'release'
